[
    {
        "version": "1.1.2",
        "downloadUrl": "https://github.com/nfourtythree/SecureAssetDownload/archive/1.1.2.zip",
        "date": "2017-07-03T09:10:00.111Z",
        "notes": [
            "[Fixed] Fixed issue with group permissions not working if user is in multiple groups"
        ]
    },
    {
        "version": "1.1.1",
        "downloadUrl": "https://github.com/nfourtythree/SecureAssetDownload/archive/1.1.1.zip",
        "date": "2016-12-07T13:59:00.111Z",
        "notes": [
            "[Fixed] Fixed typo in service /ht @tomdavies"
        ]
    },
    {
        "version": "1.1.0",
        "downloadUrl": "https://github.com/nfourtythree/SecureAssetDownload/archive/1.1.0.zip",
        "date": "2016-10-17T20:05:00.111Z",
        "notes": [
            "[Added] forceDownload variable option to allow turning off force download"
        ]
    },
    {
        "version": "1.0.3",
        "downloadUrl": "https://github.com/nfourtythree/SecureAssetDownload/archive/1.0.2.zip",
        "date": "2016-07-27T11:05:00.111Z",
        "notes": [
            "[Fixed] Issue with links not generating for assets with public urls turned off"
        ]
    },
    {
        "version": "1.0.2",
        "downloadUrl": "https://github.com/nfourtythree/SecureAssetDownload/archive/1.0.2.zip",
        "date": "2016-07-27T11:05:00.111Z",
        "notes": [
            "[Fixed] Releases links"
        ]
    },
    {
        "version": "1.0.1",
        "downloadUrl": "https://github.com/nfourtythree/SecureAssetDownload/archive/1.0.1.zip",
        "date": "2016-07-27T10:57:00.111Z",
        "notes": [
            "[Fixed] Serving from subfolders on local sources",
            "[Added] Releases JSON"
        ]
    },
    {
        "version": "1.0.1",
        "downloadUrl": "https://github.com/nfourtythree/SecureAssetDownload/archive/master.zip",
        "date": "2015-10-22T10:17:00.111Z",
        "notes": [
            "Initial Release"
        ]
    }
]
